cdk_nyancat/__init__.py
cdk_nyancat/py.typed
cdk_nyancat/_jsii/__init__.py
cdk_nyancat/_jsii/cdk-nyancat@0.0.62.jsii.tgz
cdk_nyancat-0.0.62.dist-info/LICENSE
cdk_nyancat-0.0.62.dist-info/METADATA
cdk_nyancat-0.0.62.dist-info/WHEEL
cdk_nyancat-0.0.62.dist-info/top_level.txt
cdk_nyancat-0.0.62.dist-info/RECORD
